wzqtestb.cp37-win_amd64.pyd
wzqtestb.pdb
wzqtestb-1.7.0.dist-info/METADATA
wzqtestb-1.7.0.dist-info/WHEEL
wzqtestb-1.7.0.dist-info/top_level.txt
wzqtestb-1.7.0.dist-info/RECORD
